dashboard_pkg/__init__.py
dashboard_pkg/covid_data_handler.py
dashboard_pkg/covid_news_handling.py
Covid_Dashboard_Oscar_Moores-0.1.dist-info/METADATA
Covid_Dashboard_Oscar_Moores-0.1.dist-info/WHEEL
Covid_Dashboard_Oscar_Moores-0.1.dist-info/top_level.txt
Covid_Dashboard_Oscar_Moores-0.1.dist-info/RECORD
