Metadata-Version: 2.1
Name: Covid-Dashboard-Oscar-Moores
Version: 0.1
Summary: # Covid dashboard readme  ## Introduction 
Home-page: https://github.com/FieldMarshalGaig/Covid-dashboard
Author: Oscar Moores
Author-email: om368@exeter.ac.uk
License: UNKNOWN
Platform: UNKNOWN
Classifier: Programming Language :: Python :: 3
Classifier: Operating System :: OS Independent
Requires-Python: >= 3.10.0
